hll_rcon_connection_test/__init__.py
hll_rcon_connection_test/main.py
hll_rcon_connection_test-0.1.1.dist-info/METADATA
hll_rcon_connection_test-0.1.1.dist-info/WHEEL
hll_rcon_connection_test-0.1.1.dist-info/entry_points.txt
hll_rcon_connection_test-0.1.1.dist-info/licenses/LICENSE
hll_rcon_connection_test-0.1.1.dist-info/RECORD
